neuralforecast/__init__.py
neuralforecast/auto.py
neuralforecast/compat.py
neuralforecast/core.py
neuralforecast/tsdataset.py
neuralforecast/utils.py
neuralforecast/common/__init__.py
neuralforecast/common/_base_auto.py
neuralforecast/common/_base_model.py
neuralforecast/common/_model_checks.py
neuralforecast/common/_modules.py
neuralforecast/common/_scalers.py
neuralforecast/common/enums.py
neuralforecast/losses/__init__.py
neuralforecast/losses/numpy.py
neuralforecast/losses/pytorch.py
neuralforecast/models/__init__.py
neuralforecast/models/autoformer.py
neuralforecast/models/bitcn.py
neuralforecast/models/deepar.py
neuralforecast/models/deepnpts.py
neuralforecast/models/dilated_rnn.py
neuralforecast/models/dlinear.py
neuralforecast/models/fedformer.py
neuralforecast/models/gru.py
neuralforecast/models/hint.py
neuralforecast/models/informer.py
neuralforecast/models/itransformer.py
neuralforecast/models/kan.py
neuralforecast/models/lstm.py
neuralforecast/models/mlp.py
neuralforecast/models/mlpmultivariate.py
neuralforecast/models/nbeats.py
neuralforecast/models/nbeatsx.py
neuralforecast/models/nhits.py
neuralforecast/models/nlinear.py
neuralforecast/models/patchtst.py
neuralforecast/models/rmok.py
neuralforecast/models/rnn.py
neuralforecast/models/softs.py
neuralforecast/models/stemgnn.py
neuralforecast/models/tcn.py
neuralforecast/models/tft.py
neuralforecast/models/tide.py
neuralforecast/models/timellm.py
neuralforecast/models/timemixer.py
neuralforecast/models/timesnet.py
neuralforecast/models/timexer.py
neuralforecast/models/tsmixer.py
neuralforecast/models/tsmixerx.py
neuralforecast/models/vanillatransformer.py
neuralforecast/models/xlstm.py
neuralforecast-3.1.2.dist-info/licenses/LICENSE
neuralforecast-3.1.2.dist-info/METADATA
neuralforecast-3.1.2.dist-info/WHEEL
neuralforecast-3.1.2.dist-info/top_level.txt
neuralforecast-3.1.2.dist-info/RECORD
