Metadata-Version: 2.4
Name: neuralforecast
Version: 3.1.2
Summary: Time series forecasting suite using deep learning models
Author-email: Nixtla <business@nixtla.io>
License: Apache-2.0
Project-URL: Homepage, https://github.com/Nixtla/neuralforecast/
Project-URL: Documentation, https://nixtlaverse.nixtla.io/neuralforecast/
Keywords: time-series,forecasting,deep-learning
Classifier: Development Status :: 3 - Alpha
Classifier: Intended Audience :: Developers
Classifier: Natural Language :: English
Classifier: License :: OSI Approved :: Apache Software License
Classifier: Programming Language :: Python :: 3.9
Classifier: Programming Language :: Python :: 3.10
Classifier: Programming Language :: Python :: 3.11
Classifier: Programming Language :: Python :: 3.12
Requires-Python: >=3.9
License-File: LICENSE
Requires-Dist: coreforecast>=0.0.6
Requires-Dist: fsspec
Requires-Dist: numpy>=1.21.6
Requires-Dist: pandas>=1.3.5
Requires-Dist: torch>=2.4.0
Requires-Dist: pytorch-lightning>=2.0.0
Requires-Dist: ray[tune]>=2.2.0
Requires-Dist: optuna
Requires-Dist: utilsforecast>=0.2.3
Provides-Extra: spark
Requires-Dist: fugue; extra == "spark"
Requires-Dist: pyspark>=3.5; extra == "spark"
Provides-Extra: aws
Requires-Dist: fsspec[s3]; extra == "aws"
Provides-Extra: dev
Requires-Dist: black; extra == "dev"
Requires-Dist: captum; extra == "dev"
Requires-Dist: gitpython; extra == "dev"
Requires-Dist: hyperopt; extra == "dev"
Requires-Dist: ipython<=8.32.0; extra == "dev"
Requires-Dist: matplotlib; extra == "dev"
Requires-Dist: mypy; extra == "dev"
Requires-Dist: ninja; extra == "dev"
Requires-Dist: polars; extra == "dev"
Requires-Dist: pre-commit; extra == "dev"
Requires-Dist: pyarrow; extra == "dev"
Requires-Dist: ruff; extra == "dev"
Requires-Dist: s3fs; extra == "dev"
Requires-Dist: transformers; extra == "dev"
Requires-Dist: xlstm; extra == "dev"
Requires-Dist: pytest; extra == "dev"
Requires-Dist: pytest-cov; extra == "dev"
Dynamic: license-file
